auroradns/__init__.py
auroradns/cli.py
auroradns/common/__init__.py
auroradns/common/argparser.py
auroradns/common/dnsapi.py
auroradns/common/outputs.py
auroradns/common/sysinfo.py
auroradns_cli-0.3.5.data/scripts/auroradns-cli
auroradns_cli-0.3.5.dist-info/LICENSE
auroradns_cli-0.3.5.dist-info/METADATA
auroradns_cli-0.3.5.dist-info/WHEEL
auroradns_cli-0.3.5.dist-info/entry_points.txt
auroradns_cli-0.3.5.dist-info/top_level.txt
auroradns_cli-0.3.5.dist-info/RECORD
