Metadata-Version: 2.1
Name: auroradns-cli
Version: 0.3.5
Summary: A simple CLI client for AuroraDNS
Home-page: https://gitlab.com/loekg/auroradns-cli
Author: Loek Geleijn
Author-email: loek@pcextreme.nl
Keywords: pcextreme auroradns auroradns-cli auroradns_cli
Classifier: Programming Language :: Python :: 3
Classifier: License :: OSI Approved :: MIT License
Classifier: Operating System :: POSIX
Requires-Python: >=3
License-File: LICENSE
Requires-Dist: apache-libcloud
Requires-Dist: requests
Requires-Dist: tldextract
Requires-Dist: urllib3
